isotropic/__init__.py
isotropic/e2.py
isotropic/orthonormal.py
isotropic/thetazero.py
isotropic/algos/__init__.py
isotropic/algos/grover.py
isotropic/utils/__init__.py
isotropic/utils/bisection.py
isotropic/utils/distribution.py
isotropic/utils/linalg.py
isotropic/utils/simpsons.py
isotropic/utils/state_transforms.py
isotropic-0.5.0.dist-info/licenses/LICENSE
isotropic-0.5.0.dist-info/METADATA
isotropic-0.5.0.dist-info/WHEEL
isotropic-0.5.0.dist-info/top_level.txt
isotropic-0.5.0.dist-info/RECORD
