Metadata-Version: 2.4
Name: isotropic
Version: 0.5.0
Summary: A Python package for isotropic error analysis in quantum computing
Author-email: Anurag Saha Roy <contact@anuragsaharoy.me>
License-Expression: Apache-2.0
Requires-Python: >=3.11
License-File: LICENSE
Requires-Dist: jax>=0.7.0
Requires-Dist: scipy>=1.16.0
Provides-Extra: dev
Requires-Dist: ipykernel>=6.30.1; extra == "dev"
Requires-Dist: joblib>=1.5.2; extra == "dev"
Requires-Dist: jupyter>=1.1.1; extra == "dev"
Requires-Dist: matplotlib>=3.10.6; extra == "dev"
Requires-Dist: mypy>=1.17.0; extra == "dev"
Requires-Dist: pre-commit>=4.2.0; extra == "dev"
Requires-Dist: pylatexenc>=2.10; extra == "dev"
Requires-Dist: pytest>=8.4.1; extra == "dev"
Requires-Dist: pytest-cov>=6.2.1; extra == "dev"
Requires-Dist: pytest-xdist>=3.8.0; extra == "dev"
Requires-Dist: ruff>=0.12.5; extra == "dev"
Provides-Extra: algo
Requires-Dist: qiskit~=1.2.4; extra == "algo"
Requires-Dist: qiskit-aer~=0.15.1; extra == "algo"
Provides-Extra: all
Requires-Dist: isotropic[algo,dev]; extra == "all"
Provides-Extra: docs
Requires-Dist: mkdocs>=1.6.1; extra == "docs"
Requires-Dist: mkdocs-material>=9.6.20; extra == "docs"
Requires-Dist: mkdocstrings-python>=1.18.2; extra == "docs"
Dynamic: license-file
